modelaapi/__init__.py
modelaapi/version.py
modelaapi/vim
modelaapi-0.4.136.dist-info/LICENSE.txt
modelaapi-0.4.136.dist-info/WHEEL
modelaapi-0.4.136.dist-info/METADATA
modelaapi-0.4.136.dist-info/RECORD
