Metadata-Version: 2.1
Name: modelaapi
Version: 0.4.136
Summary: data science for modela.
Home-page: https://github.com/metaprov/modela/pycode
License: MIT
Keywords: modela,automl
Author: tsagi
Author-email: tsagi@metaprov.com
Requires-Python: >=3.8,<4.0
Classifier: License :: OSI Approved :: MIT License
Classifier: Programming Language :: Python :: 3
Classifier: Programming Language :: Python :: 3.8
Classifier: Programming Language :: Python :: 3.9
Requires-Dist: grpcio (>=1.41.0,<2.0.0)
Project-URL: Repository, https://github.com/metaprov/modela/pycode
